promplate_compile-0.0.0.1.dist-info/METADATA
promplate_compile-0.0.0.1.dist-info/WHEEL
promplate_compile-0.0.0.1.dist-info/entry_points.txt
promplate_compile/__init__.py
promplate_compile/_core/__init__.py
promplate_compile/_core/template.j2
promplate_compile/api/compile.py
promplate_compile/api/watch.py
promplate_compile-0.0.0.1.dist-info/RECORD
