Metadata-Version: 2.1
Name: promplate-compile
Version: 0.0.0.1
Requires-Python: >=3.10
Requires-Dist: promplate<0.4,>=0.3.4.4
Requires-Dist: promplate-inspect~=0.0.2.2
